adformat/ADFormat.py
adformat/__init__.py
adformat-1.11.dist-info/METADATA
adformat-1.11.dist-info/WHEEL
adformat-1.11.dist-info/entry_points.txt
adformat-1.11.dist-info/top_level.txt
adformat-1.11.dist-info/RECORD
